dc_copper_cli.py
dc_copper_cli-1.0.0.dist-info/METADATA
dc_copper_cli-1.0.0.dist-info/WHEEL
dc_copper_cli-1.0.0.dist-info/entry_points.txt
dc_copper_cli-1.0.0.dist-info/RECORD
